Workbook

Sheet Deliverable
B2: CosmoGenics: Terms Proposal
B4: Scenario | D4: Scenario A | J4: Scenario B | P4: Scenario C
B5: Quarter | D5: Q1 | E5: Q2 | F5: Q3 | G5: Q4 | H5: 2026 | J5: Q1 | K5: Q2 | L5: Q3 | M5: Q4 | N5: 2026 | P5: Q1 | Q5: Q2 | R5: Q3 | S5: Q4 | T5: 2026
B6: Retail Sales ($) | D6: 30000 | E6: 40000 | F6: 55000 | G6: 75000 | H6: =SUM(D6:G6) | J6: 30000 | K6: 40000 | L6: 55000 | M6: 75000 | N6: =SUM(J6:M6) | P6: 30000 | Q6: 40000 | R6: 55000 | S6: 75000 | T6: =SUM(P6:S6)
B7: Retailer Margin (%) | D7: 0.4 | E7: 0.4 | F7: 0.4 | G7: 0.4 | H7: 0.4 | J7: 0.45 | K7: 0.45 | L7: 0.45 | M7: 0.45 | N7: 0.45 | P7: 0.5 | Q7: 0.5 | R7: 0.5 | S7: 0.5 | T7: 0.5
B8: Shipments at Retail ($) | D8: 70000 | E8: 80000 | F8: 80000 | G8: 25000 | H8: =SUM(D8:G8) | J8: 70000 | K8: 80000 | L8: 80000 | M8: 25000 | N8: =SUM(J8:M8) | P8: 70000 | Q8: 80000 | R8: 80000 | S8: 25000 | T8: =SUM(P8:S8)
B9: Wholesale Revenue ($) | D9: =(100%-D7)*D8 | E9: =(100%-E7)*E8 | F9: =(100%-F7)*F8 | G9: =(100%-G7)*G8 | H9: =SUM(D9:G9) | J9: =(100%-J7)*J8 | K9: =(100%-K7)*K8 | L9: =(100%-L7)*L8 | M9: =(100%-M7)*M8 | N9: =SUM(J9:M9) | P9: =(100%-P7)*P8 | Q9: =(100%-Q7)*Q8 | R9: =(100%-R7)*R8 | S9: =(100%-S7)*S8 | T9: =SUM(P9:S9)
B10: Marketing Allowance ($) | D10: =D11*D8 | E10: =E11*E8 | F10: =F11*F8 | G10: =G11*G8 | H10: =SUM(D10:G10) | J10: =J11*J8 | K10: =K11*K8 | L10: =L11*L8 | M10: =M11*M8 | N10: =SUM(J10:M10) | P10: =P11*P8 | Q10: =Q11*Q8 | R10: =R11*R8 | S10: =S11*S8 | T10: =SUM(P10:S10)
B11: Marketing Allowance (%) | D11: 0.03 | E11: 0.03 | F11: 0.03 | G11: 0.03 | H11: 0.03 | J11: 0.04 | K11: 0.04 | L11: 0.04 | M11: 0.04 | N11: 0.04 | P11: 0.04 | Q11: 0.04 | R11: 0.04 | S11: 0.04 | T11: 0.04
B12: Net Wholesale Revenue ($) | D12: =D9-D10 | E12: =E9-E10 | F12: =F9-F10 | G12: =G9-G10 | H12: =SUM(D12:G12) | J12: =J9-J10 | K12: =K9-K10 | L12: =L9-L10 | M12: =M9-M10 | N12: =SUM(J12:M12) | P12: =P9-P10 | Q12: =Q9-Q10 | R12: =R9-R10 | S12: =S9-S10 | T12: =SUM(P12:S12)
B13: Payment Terms (days) | D13: 30 | E13: 30 | F13: 30 | G13: 30 | J13: 60 | K13: 60 | L13: 60 | M13: 60 | P13: 60 | Q13: 60 | R13: 60 | S13: 60
B14: Cash Receipts ($) | D14: =0 | E14: =D9 | F14: =E9 | G14: =F9 | H14: =SUM(D14:G14)+G9 | J14: =0 | K14: =0 | L14: =J9 | M14: =K9 | N14: =SUM(J14:M14)+L9+M9 | P14: =0 | Q14: =0 | R14: =P9 | S14: =Q9 | T14: =SUM(P14:S14)+R9+S9
B16: Fixed Assumptions
B17: • MSRP convention: retailer assumes responsibility for markdowns (no markdown deductions applied by brand).
B18: • Cash Receipts: Net 30 shifts receipts by 1 quarter; Net 60 by 2 quarters. Annual cash receipts equal annual Wholesale Revenue.
B19: • Pipeline: AI-generated scenarios (Claude Opus 4.7) → Pydantic validation → deterministic arithmetic recompute → openpyxl rendering.

Sheet Comparison & Chart
B2: Yearly Comparison: Wholesale vs Net Wholesale Revenue
B4: Scenario | C4: Wholesale Revenue ($ | D4: Marketing Allowance ($ | E4: Net Wholesale Revenue ($ | F4: Cash Flow Lag
B5: Scenario A | C5: ='Deliverable'!H9 | D5: ='Deliverable'!H10 | E5: ='Deliverable'!H12 | F5: 1 Quarter
B6: Scenario B | C6: ='Deliverable'!N9 | D6: ='Deliverable'!N10 | E6: ='Deliverable'!N12 | F6: 2 Quarters
B7: Scenario C | C7: ='Deliverable'!T9 | D7: ='Deliverable'!T10 | E7: ='Deliverable'!T12 | F7: 2 Quarters

Sheet Executive Summary
B2: Executive Summary
B4: Recommendation: Scenario B
B6: I recommend Scenario B for the CosmoGenics account, which delivers a Total NWSR of $130,050.00 while balancing partner enablement with margin discipline. The Net 60 payment terms directly address CosmoGenics' cash flow needs during their rapid expansion phase, giving them the runway to scale operations without liquidity strain. The 4% marketing allowance provides sufficient co-op funding to power their geo-targeted social activations and live-stream campaigns in priority DMAs. At a 45% margin, we preserve healthy profitability while still demonstrating partnership commitment. The clear trade-off is that we sacrifice approximately $15,300 in NWSR versus Scenario A's shorter-terms structure, and we extend our DSO by 30 days, increasing working capital exposure. On balance, this concession is justified by the strategic upside of locking in a high-growth account and accelerating sell-through via funded digital activations.

Sheet Assumptions
B2: Assumptions, Methodology & Sensitivity
B4: MSRP | C4: Retailer follows MSRP; retailer assumes responsibility for markdowns (No markdown deductions applied by brand).
B5: Cash Receipts | C5: Computed from wholesale revenue. Net 30 shifts receipts by 1 quarter. Net 60 shifts by 2 quarters. Total receipts equal annual wholesale revenue.
B6: Sensitivity Note | C6: Changes in retailer margin within 40%-50% significantly impact baseline revenue, while marketing allowance changes within 0%-4% linearly affect the Net Wholesale Revenue after Marketing Allowance.
